FRAPP/FRAPP.py
FRAPP/PDF.py
FRAPP/__init__.py
FRAPP/loadarxiv.py
tests/__init__.py
tests/test_bold_letter.py
tests/test_end_to_end.py
tests/test_modify_word_font.py
tests/test_setup_file.py
FRAPP-1.1.1.dist-info/METADATA
FRAPP-1.1.1.dist-info/WHEEL
FRAPP-1.1.1.dist-info/top_level.txt
FRAPP-1.1.1.dist-info/RECORD
