Metadata-Version: 2.1
Name: FRAPP
Version: 1.1.1
Summary: FRAPP (Font-Facilitated Reading for Arxiv PDF Publications)
Home-page: https://github.com/mpgalleg/FRAPP
Author: MGG, QH, PP
Keywords: ArXiv Reading Accessibility
